statspack/__init__.py
statspack/binning.py
statspack/contour_pdf.py
statspack/density_contour.py
statspack/find_confidence_interval.py
statspack-0.1.2.dist-info/LICENSE
statspack-0.1.2.dist-info/METADATA
statspack-0.1.2.dist-info/WHEEL
statspack-0.1.2.dist-info/top_level.txt
statspack-0.1.2.dist-info/RECORD
