Metadata-Version: 2.1
Name: statspack
Version: 0.1.2
Summary: A statistical visualization package optimized to work with percentiles and histograms.
Home-page: https://github.com/herpichfr/statspack
Author: Fabio R Herpich
Author-email: fabio.herpich@ast.cam.ac.uk
License: GNU GENERAL PUBLIC LICENSE Version 3
Classifier: Development Status :: 3 - Alpha
Classifier: Intended Audience :: Science/Research
Classifier: License :: OSI Approved :: GNU General Public License v3 (GPLv3)
Classifier: Programming Language :: Python :: 3.8
Classifier: Programming Language :: Python :: 3.9
Classifier: Programming Language :: Python :: 3.10
Classifier: Programming Language :: Python :: 3.11
License-File: LICENSE
Requires-Dist: numpy
Requires-Dist: scipy
Requires-Dist: matplotlib
Requires-Dist: colorlog
Requires-Dist: setuptools
Requires-Dist: wheel
